tfa/__init__.py
tfa/diff.py
textanalysis-0.0.1.dist-info/LICENSE
textanalysis-0.0.1.dist-info/METADATA
textanalysis-0.0.1.dist-info/WHEEL
textanalysis-0.0.1.dist-info/top_level.txt
textanalysis-0.0.1.dist-info/RECORD
