Metadata-Version: 2.1
Name: textanalysis
Version: 0.0.1
Summary: Ways to plough through texts in search of patterns
Home-page: https://github.com/annotation/textanalysis
Author: Dirk Roorda
Author-email: text.annotation@icloud.com
License: UNKNOWN
Keywords: text,linguistics,graph
Platform: UNKNOWN
Classifier: Development Status :: 4 - Beta
Classifier: Environment :: Other Environment
Classifier: Framework :: Jupyter
Classifier: Intended Audience :: Developers
Classifier: Intended Audience :: Education
Classifier: Intended Audience :: Science/Research
Classifier: License :: OSI Approved :: MIT License
Classifier: Natural Language :: English
Classifier: Operating System :: MacOS :: MacOS X
Classifier: Operating System :: Microsoft :: Windows :: Windows 10
Classifier: Operating System :: POSIX :: Linux
Classifier: Programming Language :: Python :: 3 :: Only
Classifier: Programming Language :: Python :: Implementation :: CPython
Classifier: Topic :: Scientific/Engineering :: Information Analysis
Classifier: Topic :: Text Processing :: Filters
Classifier: Topic :: Text Processing :: Linguistic
Classifier: Topic :: Text Processing :: Markup
Requires-Python: >=3.9.0
License-File: LICENSE
Requires-Dist: wheel
Requires-Dist: python-levenshtein
Requires-Dist: ipython
